MANIFEST.in
README.md
setup.cfg
setup.py
braviarc/__init__.py
braviarc/braviarc.py
braviarc_homeassistant.egg-info/PKG-INFO
braviarc_homeassistant.egg-info/SOURCES.txt
braviarc_homeassistant.egg-info/dependency_links.txt
braviarc_homeassistant.egg-info/not-zip-safe
braviarc_homeassistant.egg-info/requires.txt
braviarc_homeassistant.egg-info/top_level.txt