Metadata-Version: 1.2
Name: braviarc-homeassistant
Version: 0.3.7.dev0
Summary: # BraviaRC Python Package
